./.gitignore
./LICENSE
./PKG-INFO
./README.md
./f1_server.py
./mcp-publisher
./pyproject.toml
./server.json
./registry/.env.example
./registry/.gitignore
./registry/.golangci.yml
./registry/.goreleaser.yaml
./registry/.ko.dockerignore
./registry/.ko.yaml
./registry/CLAUDE.md
./registry/LICENSE
./registry/Makefile
./registry/README.md
./registry/complete.md
./registry/docker-compose.yml
./registry/go.mod
./registry/go.sum
./registry/.githooks/pre-commit
./registry/.github/dependabot.yml
./registry/.github/workflows/cancel-pulumi-lock.yml
./registry/.github/workflows/ci.yml
./registry/.github/workflows/claude.yml
./registry/.github/workflows/deploy-production.yml
./registry/.github/workflows/deploy-staging.yml
./registry/.github/workflows/release.yml
./registry/.github/workflows/sync-db.yml
./registry/.github/workflows/sync-schema.yml
./registry/cmd/publisher/README.md
./registry/cmd/publisher/main.go
./registry/cmd/publisher/auth/common.go
./registry/cmd/publisher/auth/dns.go
./registry/cmd/publisher/auth/github-at.go
./registry/cmd/publisher/auth/github-oidc.go
./registry/cmd/publisher/auth/http.go
./registry/cmd/publisher/auth/interface.go
./registry/cmd/publisher/auth/none.go
./registry/cmd/publisher/auth/azurekeyvault/common.go
./registry/cmd/publisher/auth/googlekms/common.go
./registry/cmd/publisher/commands/init.go
./registry/cmd/publisher/commands/login.go
./registry/cmd/publisher/commands/logout.go
./registry/cmd/publisher/commands/publish.go
./registry/cmd/publisher/commands/publish_test.go
./registry/cmd/publisher/commands/validate.go
./registry/cmd/registry/main.go
./registry/data/seed.json
./registry/deploy/.gitignore
./registry/deploy/Makefile
./registry/deploy/Pulumi.gcpProd.yaml
./registry/deploy/Pulumi.gcpStaging.yaml
./registry/deploy/Pulumi.local.yaml
./registry/deploy/Pulumi.yaml
./registry/deploy/README.md
./registry/deploy/go.mod
./registry/deploy/go.sum
./registry/deploy/main.go
./registry/deploy/pkg/k8s/backup.go
f1_mcp-0.1.3.dist-info/METADATA
f1_mcp-0.1.3.dist-info/WHEEL
f1_mcp-0.1.3.dist-info/entry_points.txt
f1_mcp-0.1.3.dist-info/licenses/LICENSE
f1_mcp-0.1.3.dist-info/RECORD
