Metadata-Version: 2.4
Name: f1-mcp
Version: 0.1.3
Summary: MCP server for Formula 1 data - provides F1 telemetry, race results, standings, and analytics for Claude Desktop
Author-email: Rajat <driven.rajat@gmail.com>
License: MIT
License-File: LICENSE
Keywords: claude,f1,formula1,mcp,racing,telemetry
Classifier: Development Status :: 4 - Beta
Classifier: Intended Audience :: Developers
Classifier: Intended Audience :: Education
Classifier: Intended Audience :: End Users/Desktop
Classifier: Intended Audience :: Information Technology
Classifier: Intended Audience :: Science/Research
Classifier: License :: OSI Approved :: MIT License
Classifier: Programming Language :: Python :: 3
Classifier: Programming Language :: Python :: 3.10
Classifier: Programming Language :: Python :: 3.11
Classifier: Programming Language :: Python :: 3.12
Classifier: Topic :: Games/Entertainment
Requires-Python: >=3.10
Requires-Dist: fastf1>=3.0.0
Requires-Dist: fastmcp>=0.1.0
Requires-Dist: matplotlib>=3.7.0
Requires-Dist: mcp>=1.0.0
Requires-Dist: numpy>=1.24.0
Requires-Dist: pandas>=2.0.0
Requires-Dist: requests>=2.28.0
Provides-Extra: dev
Requires-Dist: black>=23.0.0; extra == 'dev'
Requires-Dist: pytest-asyncio>=0.21.0; extra == 'dev'
Requires-Dist: pytest>=7.0.0; extra == 'dev'
Requires-Dist: ruff>=0.1.0; extra == 'dev'
